README.md
setup.py
MF_StatusCode/__init__.py
MF_StatusCode/app.py
MF_StatusCode.egg-info/PKG-INFO
MF_StatusCode.egg-info/SOURCES.txt
MF_StatusCode.egg-info/dependency_links.txt
MF_StatusCode.egg-info/top_level.txt