Metadata-Version: 1.2
Name: MF-StatusCode
Version: 1.0.1
Summary: 蝰蛇软件工作室-状态管理包
Home-page: https://git-codecommit.us-west-2.amazonaws.com/v1/repos/MF_statusCode_python
Author: 林睿霖
Author-email: limitlin@outlook.com
Maintainer: 林睿霖
Maintainer-email: limitlin@outlook.com
License: UNKNOWN
Platform: UNKNOWN
